pytera-0.1.1.dist-info/METADATA
pytera-0.1.1.dist-info/WHEEL
pytera/__init__.py
pytera/_core.abi3.so
pytera/_core.pyi
pytera/py.typed
pytera-0.1.1.dist-info/RECORD
