Metadata-Version: 2.4
Name: pytera
Version: 0.1.1
Classifier: Development Status :: 3 - Alpha
Classifier: Intended Audience :: Developers
Classifier: License :: OSI Approved :: MIT License
Classifier: Operating System :: OS Independent
Classifier: Programming Language :: Python :: 3
Classifier: Programming Language :: Python :: 3.8
Classifier: Programming Language :: Python :: 3.9
Classifier: Programming Language :: Python :: 3.10
Classifier: Programming Language :: Python :: 3.11
Classifier: Programming Language :: Python :: 3.12
Classifier: Programming Language :: Python :: 3.13
Classifier: Programming Language :: Rust
Classifier: Topic :: Internet :: WWW/HTTP :: Dynamic Content
Classifier: Topic :: Software Development :: Libraries :: Python Modules
Classifier: Topic :: Text Processing :: Markup :: HTML
Classifier: Topic :: Text Processing :: Markup :: XML
Summary: A fast, Python templating engine powered by Rust's Tera library
Keywords: templating,tera,rust,pyo3,jinja2,django-templates,web-framework,html,rendering,fast
Author-email: un4gt <mt3085570450@outlook.com>
Maintainer-email: un4gt <mt3085570450@outlook.com>
License: MIT
Requires-Python: >=3.8.1
Project-URL: Homepage, https://github.com/PyO3Lab/pytera
Project-URL: Documentation, https://github.com/PyO3Lab/pytera#readme
Project-URL: Repository, https://github.com/PyO3Lab/pytera.git
Project-URL: Issues, https://github.com/PyO3Lab/pytera/issues
Project-URL: Changelog, https://github.com/PyO3Lab/pytera/blob/main/CHANGELOG.md
